{
  "project_info": {
    "project_number": "628235752786",
    "project_id": "wedeal-8b009",
    "storage_bucket": "wedeal-8b009.firebasestorage.app"
  },
  "client": [
    {
      "client_info": {
        "mobilesdk_app_id": "1:628235752786:android:f7e4b23dbfc3db0986568b",
        "android_client_info": {
          "package_name": "com.example.wedeal"
        }
      },
      "oauth_client": [],
      "api_key": [
        {
          "current_key": "AIzaSyAzAQixpb1FIdea3e3L4asf_spDKrIVweU"
        }
      ],
      "services": {
        "appinvite_service": {
          "other_platform_oauth_client": []
        }
      }
    }
  ],
  "configuration_version": "1"
}